django_ray/__init__.py
django_ray/admin.py
django_ray/apps.py
django_ray/backends.py
django_ray/logging.py
django_ray/models.py
django_ray/conf/__init__.py
django_ray/conf/defaults.py
django_ray/conf/settings.py
django_ray/management/__init__.py
django_ray/management/commands/__init__.py
django_ray/management/commands/django_ray_worker.py
django_ray/migrations/0001_initial.py
django_ray/migrations/__init__.py
django_ray/runner/__init__.py
django_ray/runner/base.py
django_ray/runner/cancellation.py
django_ray/runner/leasing.py
django_ray/runner/ray_core.py
django_ray/runner/ray_job.py
django_ray/runner/reconciliation.py
django_ray/runner/retry.py
django_ray/runtime/__init__.py
django_ray/runtime/distributed.py
django_ray/runtime/entrypoint.py
django_ray/runtime/import_utils.py
django_ray/runtime/serialization.py
django_ray-0.1.1.dist-info/METADATA
django_ray-0.1.1.dist-info/WHEEL
django_ray-0.1.1.dist-info/licenses/LICENSE
django_ray-0.1.1.dist-info/RECORD
