Metadata-Version: 2.4
Name: django-ray
Version: 0.1.1
Summary: Ray-based backend for Django Tasks with distributed execution and database-backed reliability
Project-URL: Homepage, https://github.com/dariuszpanas/django-ray
Project-URL: Documentation, https://github.com/dariuszpanas/django-ray/tree/main/docs
Project-URL: Repository, https://github.com/dariuszpanas/django-ray
Project-URL: Issues, https://github.com/dariuszpanas/django-ray/issues
Author: Dariusz Panas
License-Expression: BSD-3-Clause
License-File: LICENSE
Keywords: async,background-tasks,distributed,django,ray,task-queue,tasks
Classifier: Development Status :: 4 - Beta
Classifier: Environment :: Web Environment
Classifier: Framework :: Django
Classifier: Framework :: Django :: 6.0
Classifier: Intended Audience :: Developers
Classifier: License :: OSI Approved :: BSD License
Classifier: Operating System :: OS Independent
Classifier: Programming Language :: Python :: 3
Classifier: Programming Language :: Python :: 3.12
Classifier: Programming Language :: Python :: 3.13
Classifier: Topic :: Software Development :: Libraries :: Python Modules
Classifier: Topic :: System :: Distributed Computing
Requires-Python: >=3.12
Requires-Dist: django>=6.0
Requires-Dist: ray[default]>=2.53.0
Provides-Extra: postgres
Requires-Dist: psycopg[binary]>=3.1; extra == 'postgres'
